{"title": "beschlagnahmt", "id": "tg-681702547865468929", "net.maunium.telegram.pack": {"short_name": "Alaaaarm", "hash": "1805007190"}, "stickers": [{"body": "🚨", "url": "mxc://matrix.batcave420.de/xRYrQFIsIzUGveQdUFIdhvBo", "info": {"w": 251, "h": 256, "size": 221075, "mimetype": "image/png", "thumbnail_url": "mxc://matrix.batcave420.de/xRYrQFIsIzUGveQdUFIdhvBo", "thumbnail_info": {"w": 251, "h": 256, "size": 221075, "mimetype": "image/png"}}, "msgtype": "m.sticker", "id": "tg-681702547865472558", "net.maunium.telegram.sticker": {"pack": {"id": "681702547865468929", "short_name": "Alaaaarm"}, "id": "681702547865472558", "emoticons": ["🚨"]}}]}